{"content":[{"id":"4be7d17e","settings":[],"elements":[{"id":"433d1c13","settings":{"_column_size":100,"_inline_size":null},"elements":[{"id":"50c663a4","settings":{"classic_meta_separator":"\/\/\/","classic_read_more_text":"Read More \u00bb","cards_meta_separator":"\u2022","cards_read_more_text":"Read More \u00bb","full_content_meta_separator":"\/\/\/","posts_post_type":"current_query","pagination_page_limit":"5","pagination_prev_label":"&laquo; Previous","pagination_next_label":"Next &raquo;","text":"Load More","load_more_no_posts_custom_message":"No more posts to show","__dynamic__":{"posts_query_id":"[elementor-tag id=\"d3b3525\" name=\"post-terms\" settings=\"%7B%22separator%22%3A%22%2C%20%22%7D\"]"}},"elements":[],"isInner":false,"widgetType":"posts","elType":"widget"}],"isInner":false,"elType":"column"}],"isInner":false,"elType":"section"},{"id":"729ae7b9","settings":[],"elements":[{"id":"dec6325","settings":{"_column_size":100,"_inline_size":null},"elements":[{"id":"50a97ed1","settings":{"classic_meta_separator":"\/\/\/","classic_read_more_text":"Read More \u00bb","cards_meta_separator":"\u2022","cards_read_more_text":"Read More \u00bb","full_content_meta_separator":"\/\/\/","posts_post_type":"current_query","pagination_page_limit":"5","pagination_prev_label":"&laquo; Previous","pagination_next_label":"Next &raquo;","text":"Load More","load_more_no_posts_custom_message":"No more posts to show","__dynamic__":{"posts_query_id":"[elementor-tag id=\"84b0733\" name=\"post-terms\" settings=\"%7B%22separator%22%3A%22%2C%20%22%7D\"]"}},"elements":[],"isInner":false,"widgetType":"posts","elType":"widget"}],"isInner":false,"elType":"column"}],"isInner":false,"elType":"section"}],"settings":{"template":"default"},"metadata":[]}